README
setup.cfg
setup.py
tweethon.py
tweethon.egg-info/PKG-INFO
tweethon.egg-info/SOURCES.txt
tweethon.egg-info/dependency_links.txt
tweethon.egg-info/requires.txt
tweethon.egg-info/top_level.txt