Metadata-Version: 1.0
Name: tweethon
Version: 0.8.1
Summary: A python wrapper around the Twitter API
Home-page: http://bitbucket.org/jrossi/tweethon/
Author: Jeremy Rossi
Author-email: jeremy@jeremyrossi.com
License: Apache License 2.0
Keywords: twitter api
Platform: UNKNOWN
Classifier: Development Status :: 4 - Beta
Classifier: Intended Audience :: Developers
Classifier: License :: OSI Approved :: Apache Software License
Classifier: Topic :: Software Development :: Libraries :: Python Modules
Classifier: Topic :: Communications :: Chat
Classifier: Topic :: Internet
